[{"timestamp":1669976034680,"url_object":{"domain":"www.example.com","path":"/xwd/egj","query_object":{"var4":"62"},"hash":"#x;nztmzc"},"ec":{"et":"ur"}},{"timestamp":1669976034680,"url_object":{"domain":"www.example.com","path":"/xwd/egj","query_object":{"var4":"62"},"hash":"#x;nztmzc"},"ec":{"et":"j","er":{"m":"general error","s":"call stack","l":37}}},{"timestamp":1669976034680,"url_object":{"domain":"www.example.com","path":"/xwd/egj","query_object":{"var4":"62"},"hash":"#x;nztmzc"},"ec":{"et":"v","p":["event1"]}},{"timestamp":1669976034680,"url_object":{"domain":"www.example.com","path":"/xwd/egj","query_object":{"var4":"62"},"hash":"#x;nztmzc"},"ec":{"et":"ur"}},{"timestamp":1669976034680,"url_object":{"domain":"www.example.com","path":"/xwd/egj","query_object":{"var4":"62"},"hash":"#x;nztmzc"},"ec":{"et":"j","er":{"m":"general error","s":"call stack","l":12}}}]